eligibility_api/__init__.py
eligibility_api/client.py
eligibility_api/server.py
eligibility_api/tokens.py
eligibility_api-2025.4.1.dist-info/licenses/LICENSE
eligibility_api-2025.4.1.dist-info/METADATA
eligibility_api-2025.4.1.dist-info/WHEEL
eligibility_api-2025.4.1.dist-info/top_level.txt
eligibility_api-2025.4.1.dist-info/RECORD
