Metadata-Version: 2.4
Name: eligibility-api
Version: 2025.4.1
Summary: Data exchange to verify eligibility for transit benefits.
License:                                  Apache License
Project-URL: code, https://github.com/cal-itp/eligibility-api
Project-URL: tracker, https://github.com/cal-itp/eligibility-api/issues
Classifier: Programming Language :: Python :: 3 :: Only
Classifier: License :: OSI Approved :: Apache Software License
Classifier: Operating System :: OS Independent
Requires-Python: >=3.9
License-File: LICENSE
Requires-Dist: jwcrypto>=1.5
Requires-Dist: requests>=2.31.0
Provides-Extra: dev
Requires-Dist: black; extra == "dev"
Requires-Dist: build; extra == "dev"
Requires-Dist: flake8; extra == "dev"
Requires-Dist: pre-commit; extra == "dev"
Provides-Extra: test
Requires-Dist: coverage; extra == "test"
Requires-Dist: pytest; extra == "test"
Requires-Dist: pytest-mock; extra == "test"
Requires-Dist: responses; extra == "test"
Dynamic: license-file
